vsr53/AccessCodes.py
vsr53/Commands.py
vsr53/DisplayModes.py
vsr53/ErrorMessages.py
vsr53/ThyrCommPackage.py
vsr53/__init__.py
vsr53/_version.py
vsr53/logger.py
vsr53/vsr53.py
vsr53-1.1.1.dist-info/METADATA
vsr53-1.1.1.dist-info/WHEEL
vsr53-1.1.1.dist-info/licenses/LICENSE
vsr53-1.1.1.dist-info/RECORD
