Metadata-Version: 2.1
Name: vsr53
Version: 1.1.1
Summary: Python Library to interface with Thyracont's VSR53 vacuum gauges
Project-URL: Download, https://github.com/lobis/vsr53/releases
Project-URL: Homepage, https://github.com/lobis/vsr53
Project-URL: Bug Tracker, https://github.com/lobis/vsr53/issues
Author-email: Oscar Martínez <omartinez@ifae.es>, Luis Antonio Obis Aparicio <luis@obis.dev>
Maintainer-email: Luis Antonio Obis Aparicio <luis@obis.dev>
License-Expression: CC0-1.0
License-File: LICENSE
Classifier: Operating System :: OS Independent
Classifier: Programming Language :: Python :: 3
Requires-Python: >=3.8
Requires-Dist: pyserial
Provides-Extra: test
Requires-Dist: pre-commit; extra == 'test'
Requires-Dist: pytest; extra == 'test'
